httpstan
