Metadata-Version: 2.1
Name: httpstan
Version: 0.8.0
Summary: HTTP-based interface to Stan, a package for Bayesian inference.
Home-page: UNKNOWN
Author: httpstan developers
Author-email: UNKNOWN
License: UNKNOWN
Platform: UNKNOWN
Classifier: Intended Audience :: Science/Research
Classifier: License :: OSI Approved :: ISC License (ISCL)
Classifier: Programming Language :: Cython
Classifier: Programming Language :: Python
Classifier: Programming Language :: Python :: 3
Classifier: Programming Language :: Python :: 3.6
Requires-Dist: pbr (<5,>=4.0)
Requires-Dist: aiohttp (<4,>=3.2.1)
Requires-Dist: appdirs (<2,>=1.4.3)
Requires-Dist: webargs (<6,>=5)
Requires-Dist: marshmallow (<4,>=3.0.0rc4)
Requires-Dist: numpy (<2,>=1.7)
Requires-Dist: Cython (<4,>=0.29)
Requires-Dist: apispec (<1,>=0.21)
Requires-Dist: protobuf (<4,>=3.3.0)
Requires-Dist: setuptools (>=28.8)
Requires-Dist: ujson (<2,>=1.3)
Requires-Dist: uvloop (<1,>=0.11.2) ; (sys_platform != "win32" or implementation_name == "PyPy")
